debouncer/__init__.py
debouncer/debounce.py
python_debouncer-0.1.5.dist-info/LICENSE
python_debouncer-0.1.5.dist-info/METADATA
python_debouncer-0.1.5.dist-info/WHEEL
python_debouncer-0.1.5.dist-info/entry_points.txt
python_debouncer-0.1.5.dist-info/RECORD
