Metadata-Version: 2.1
Name: python-debouncer
Version: 0.1.5
Summary: Debouncer and friends for Python
License: Apache-2.0
Author: Sassan Haradji
Author-email: sassanh@gmail.com
Requires-Python: >=3.9,<4.0
Classifier: License :: OSI Approved :: Apache Software License
Classifier: Programming Language :: Python :: 3
Classifier: Programming Language :: Python :: 3.9
Classifier: Programming Language :: Python :: 3.10
Classifier: Programming Language :: Python :: 3.11
Classifier: Programming Language :: Python :: 3.12
Requires-Dist: python-immutable (>=1.0.4,<2.0.0)
